tests
x_cms
