Metadata-Version: 1.1
Name: xcms
Version: 0.1.4
Summary: calculated extended contact mode score provided the query and template protein-ligand structures
Home-page: https://github.com/EricTing/extended-cms
Author: Yun Ding
Author-email: yding8@lsu.edu
License: GPLv3+
Platform: Unix-like
Classifier: Development Status :: 4 - Beta
Classifier: Environment :: Console
Classifier: Intended Audience :: Science/Research
Classifier: License :: OSI Approved :: GNU General Public License v3 or later (GPLv3+)
Classifier: Operating System :: POSIX
Classifier: Operating System :: MacOS
Classifier: Operating System :: Unix
Classifier: Programming Language :: Python :: 2
Classifier: Topic :: Scientific/Engineering :: Bio-Informatics
